pyunigen.pypy38-pp73-darwin.so
pyunigen-2.5.8.dist-info/RECORD
pyunigen-2.5.8.dist-info/LICENSE
pyunigen-2.5.8.dist-info/WHEEL
pyunigen-2.5.8.dist-info/top_level.txt
pyunigen-2.5.8.dist-info/METADATA
